README.md
setup.py
sentry_wechat_plugin.egg-info/PKG-INFO
sentry_wechat_plugin.egg-info/SOURCES.txt
sentry_wechat_plugin.egg-info/dependency_links.txt
sentry_wechat_plugin.egg-info/entry_points.txt
sentry_wechat_plugin.egg-info/not-zip-safe
sentry_wechat_plugin.egg-info/requires.txt
sentry_wechat_plugin.egg-info/top_level.txt
wechat/__init__.py
wechat/plugin.py