Metadata-Version: 2.1
Name: sentry-wechat-plugin
Version: 1.3
Summary: A Sentry extension which send errors stats to WeChat.
Home-page: https://github.com/chenshaorong/sentry-wechat-plugin
Author: shaorong.chen
Author-email: shaorong.chen@aliyun.com
License: MIT
Keywords: sentry wechat
Platform: UNKNOWN
Classifier: Programming Language :: Python :: 2.7
Classifier: Topic :: Utilities
Classifier: License :: OSI Approved :: MIT License
